helx_agents/__init__.py
helx_agents/_version.py
helx_agents/losses.py
helx_agents/memory.py
helx_agents/modules.py
helx_agents/preprocess.py
helx_agents/agents/__init__.py
helx_agents/agents/agent.py
helx_agents/agents/ddqn.py
helx_agents/agents/dqn.py
helx_agents/agents/dueling_dqn.py
helx_agents/agents/random.py
helx_agents/agents/sac.py
helx_agents/agents/sacd.py
HELX_agents-1.0.2.dist-info/AUTHORS
HELX_agents-1.0.2.dist-info/LICENSE
HELX_agents-1.0.2.dist-info/METADATA
HELX_agents-1.0.2.dist-info/NOTICE
HELX_agents-1.0.2.dist-info/WHEEL
HELX_agents-1.0.2.dist-info/top_level.txt
HELX_agents-1.0.2.dist-info/RECORD
